proved/__init__.py
proved/proved.py
proved/xes_keys.py
proved/algorithms/__init__.py
proved/algorithms/conformance/__init__.py
proved/algorithms/conformance/alignments/__init__.py
proved/algorithms/conformance/alignments/alignment_bounds_su.py
proved/artifacts/__init__.py
proved/artifacts/behavior_graph/__init__.py
proved/artifacts/behavior_graph/behavior_graph.py
proved/artifacts/behavior_net/__init__.py
proved/artifacts/behavior_net/behavior_net.py
proved/artifacts/behavior_net/utils.py
proved/metrics/__init__.py
proved/metrics/trace_metrics.py
proved/simulation/__init__.py
proved/simulation/bewilderer/__init__.py
proved/simulation/bewilderer/add_activities.py
proved/simulation/bewilderer/add_indeterminate_events.py
proved/simulation/bewilderer/add_timestamps.py
proved/simulation/bewilderer/add_uncertainty.py
proved/visualizations/__init__.py
proved/visualizations/graphviz/__init__.py
proved/visualizations/graphviz/behavior_graph.py
tests/__init__.py
tests/test_proved.py
proved-0.1.1.dist-info/AUTHORS.rst
proved-0.1.1.dist-info/LICENSE
proved-0.1.1.dist-info/METADATA
proved-0.1.1.dist-info/WHEEL
proved-0.1.1.dist-info/top_level.txt
proved-0.1.1.dist-info/RECORD
