Metadata-Version: 2.1
Name: proved
Version: 0.1.1
Summary: PROVED (PRocess mining OVer uncErtain Data) is a collection of tools to perform process mining on uncertain event data.
Home-page: https://github.com/marcopegoraro/proved
Author: Marco Pegoraro
Author-email: pegoraro@pads.rwth-aachen.de
License: GNU General Public License v3
Keywords: proved,process mining,data science,process discovery,conformance checking
Platform: UNKNOWN
Classifier: Development Status :: 3 - Alpha
Classifier: Intended Audience :: Developers
Classifier: License :: OSI Approved :: GNU General Public License v3 (GPLv3)
Classifier: Natural Language :: English
Classifier: Programming Language :: Python :: 3
Classifier: Programming Language :: Python :: 3.4
Classifier: Programming Language :: Python :: 3.5
Classifier: Programming Language :: Python :: 3.6
Classifier: Programming Language :: Python :: 3.7
Requires-Python: >=3.6
Requires-Dist: pm4py (==1.2.12)
Requires-Dist: pm4pycvxopt (==0.0.5)
Requires-Dist: networkx (==2.4)
Requires-Dist: setuptools (==40.8.0)
Requires-Dist: lxml (==4.6.2)
Requires-Dist: matplotlib (==3.1.2)
Requires-Dist: Pympler (==0.8)
Requires-Dist: graphviz (==0.13.2)
